allure_custom/__init__.py
allure_custom/__version__.py
allure_custom/conf.py
allure_custom/default_allure/bin/allure
allure_custom/default_allure/bin/allure.bat
allure_custom/default_allure/config/allure-cucumber.yml
allure_custom/default_allure/config/allure-junit.yml
allure_custom/default_allure/config/allure.yml
allure_custom/default_allure/lib/allure-commandline-2.22.0.jar
allure_custom/default_allure/lib/allure-generator-2.22.0.jar
allure_custom/default_allure/lib/allure-model-2.20.1.jar
allure_custom/default_allure/lib/allure-plugin-api-2.22.0.jar
allure_custom/default_allure/lib/allure1-model-1.0.jar
allure_custom/default_allure/lib/annotations-15.0.jar
allure_custom/default_allure/lib/commons-beanutils-1.9.4.jar
allure_custom/default_allure/lib/commons-codec-1.11.jar
allure_custom/default_allure/lib/commons-collections-3.2.2.jar
allure_custom/default_allure/lib/commons-collections4-4.2.jar
allure_custom/default_allure/lib/commons-io-2.11.0.jar
allure_custom/default_allure/lib/commons-lang3-3.12.0.jar
allure_custom/default_allure/lib/commons-logging-1.2.jar
allure_custom/default_allure/lib/commons-text-1.3.jar
allure_custom/default_allure/lib/flexmark-0.62.2.jar
allure_custom/default_allure/lib/flexmark-ext-tables-0.62.2.jar
allure_custom/default_allure/lib/flexmark-util-0.62.2.jar
allure_custom/default_allure/lib/flexmark-util-ast-0.62.2.jar
allure_custom/default_allure/lib/flexmark-util-builder-0.62.2.jar
allure_custom/default_allure/lib/flexmark-util-collection-0.62.2.jar
allure_custom/default_allure/lib/flexmark-util-data-0.62.2.jar
allure_custom/default_allure/lib/flexmark-util-dependency-0.62.2.jar
allure_custom/default_allure/lib/flexmark-util-format-0.62.2.jar
allure_custom/default_allure/lib/flexmark-util-html-0.62.2.jar
allure_custom/default_allure/lib/flexmark-util-misc-0.62.2.jar
allure_custom/default_allure/lib/flexmark-util-options-0.62.2.jar
allure_custom/default_allure/lib/flexmark-util-sequence-0.62.2.jar
allure_custom-2024.5.24.dist-info/METADATA
allure_custom-2024.5.24.dist-info/WHEEL
allure_custom-2024.5.24.dist-info/licenses/LICENSE
allure_custom-2024.5.24.dist-info/RECORD
