Metadata-Version: 2.1
Name: allure-custom
Version: 2024.5.24
Summary: allure custom
Project-URL: Source, https://github.com/funny-dream/allure-custom
Project-URL: Documentation, https://funny-dream.github.io/allure-custom
Author-email: mikigo <1964191531@qq.com>
License-File: LICENSE
Classifier: License :: OSI Approved :: Apache Software License
Classifier: Operating System :: OS Independent
Classifier: Programming Language :: Python :: 3
Requires-Python: >=3.6
Provides-Extra: doc
Requires-Dist: mkdocs-material; extra == 'doc'
Provides-Extra: test
Requires-Dist: pytest; extra == 'test'
